LICENSE
MANIFEST.in
README.md
setup.cfg
setup.py
opencity/API_helper.py
opencity/VERSION
opencity/__init__.py
opencity/config.py
opencity/fetch_dataset_list.py
opencity/opencity.py
opencity.egg-info/PKG-INFO
opencity.egg-info/SOURCES.txt
opencity.egg-info/dependency_links.txt
opencity.egg-info/requires.txt
opencity.egg-info/top_level.txt
opencity/fetcher/__init__.py
opencity/fetcher/basic_fetcher.py
opencity/fetcher/csv_fetcher.py
opencity/fetcher/json_fetcher.py
opencity/fetcher/kml_fetcher.py
opencity/fetcher/shp_fetcher.py
opencity/fetcher/txt_fetcher.py
opencity/fetcher/xls_fetcher.py
opencity/tests/__init__.py
opencity/tests/test_dataset_url_fetcher.py
opencity/tests/test_functional.py
opencity/tests/test_get_data.py
opencity/tests/test_save_data.py
opencity/tests/test_show_data.py
opencity/tests/test_API_helper/__init__.py
opencity/tests/test_API_helper/test_fetch_helper.py
opencity/tests/test_API_helper/test_id_helper.py
opencity/tests/test_API_helper/test_show_data_helper.py
opencity/tests/test_fetcher/__init__.py
opencity/tests/test_fetcher/test_basic_fetcher.py
opencity/tests/test_fetcher/test_csv_fetcher.py
opencity/tests/test_fetcher/test_json_fetcher.py
opencity/tests/test_fetcher/test_kml_fetcher.py
opencity/tests/test_fetcher/test_shp_fetcher.py
opencity/tests/test_fetcher/test_txt_fetcher.py
opencity/tests/test_fetcher/xls_fetcher.py