Metadata-Version: 2.1
Name: opencity
Version: 1.0.1
Summary: Client for OpenData DKAN-API
Home-page: UNKNOWN
Author: Silke Husse, Rahkakavee Baskaran, Birke Pfeifle, Tilman Kerl
Author-email: konstanz@correlaid.org
License: MIT
Platform: UNKNOWN
Requires-Python: >=3.7
License-File: LICENSE
